pretty_errors/__init__.py
pretty_errors/__main__.py
pretty_errors-1.2.25.dist-info/LICENSE
pretty_errors-1.2.25.dist-info/METADATA
pretty_errors-1.2.25.dist-info/WHEEL
pretty_errors-1.2.25.dist-info/top_level.txt
pretty_errors-1.2.25.dist-info/RECORD
