Metadata-Version: 2.1
Name: pretty_errors
Version: 1.2.25
Summary: Prettifies Python exception output to make it legible.
Home-page: https://github.com/onelivesleft/PrettyErrors/
Author: Iain King
Author-email: iain.king@gmail.com
License: UNKNOWN
Platform: UNKNOWN
Classifier: Programming Language :: Python :: 3
Classifier: Programming Language :: Python :: 2
Classifier: License :: OSI Approved :: MIT License
Classifier: Operating System :: OS Independent
